complete/__init__.py
complete-0.0.1.dist-info/METADATA
complete-0.0.1.dist-info/WHEEL
complete-0.0.1.dist-info/top_level.txt
complete-0.0.1.dist-info/RECORD
