Metadata-Version: 2.1
Name: complete
Version: 0.0.1
Summary: A Python library to autocomplete questions using search engines
Home-page: UNKNOWN
Author: DankCoder
Author-email: business.dankcoder@gmail.com
License: UNKNOWN
Platform: UNKNOWN
Classifier: Programming Language :: Python :: 3
Classifier: License :: OSI Approved :: MIT License
Classifier: Operating System :: OS Independent
Requires-Python: >=3.6
Requires-Dist: aiohttp
Requires-Dist: requests
Requires-Dist: lxml
